[
    {
        "name": "null",
        "preposition": "null"
    },
    {
        "name": "your house",
        "preposition": "in",
        "music": "insidehouse.mp3",
		"bg": "insidehouse.png",
        "commands": [
            "sleep"
        ],
        "inspect_list": [
            {
                "name": "front door",
                "type": "door",
                "door_target": 2,
                "message": "The front door to your home. It leads outside."
            },
            {
                "name": "bed",
                "type": "bed",
                "message": "It's just your bed."
            },
            {
                "name": "bookshelf",
                "type": "message",
                "message": "It's an elegant, hand-crafted bookshelf."
            }
        ]
    },
    {
        "name": "your house",
        "preposition": "outside",
        "music": "outsidehouse.mp3",
	"bg": "outsidehouse.png",
        "commands": [
            "throw brick at window"
        ],
        "inspect_list": [
            {
                "name": "front door",
                "type": "door",
                "door_target": 1,
                "message": "The front door to your home. It leads inside."
            },
            {
                "name": "vines",
                "type": "message",
                "message": "Some vines are growing up the side of your home."
            },
            {
                "name": "window",
                "type": "window",
                "smashed": false,
                "message": "One of the windows on your house."
            },
            {
                "name": "dirt path",
                "type": "door",
                "door_target": 3,
                "message": "This path leads to the forest."
            }
        ]
    },
    {
        "name": "the forest",
        "preposition": "in",
        "music": "forest.mp3",
        "bg": "forest.png",
        "inspect_list": [
            {
                "name": "dirt path",
                "type": "door",
                "door_target": 2,
                "message": "This path leads back to your house."
            },
            {
                "name": "deeper forest",
                "type": "door",
                "door_target": 4,
                "message": "It's only more woods ahead. The path ends here."
            }
        ]
    },
    {
        "name": "the deeper forest",
        "preposition": "in",
        "music": "forest.mp3",
        "bg": "deeperforest.png",
        "inspect_list": [
            {
                "name": "way back",
                "type": "door",
                "door_target": 3,
                "message": "You still have the option to go back."
            },
            {
                "name": "cave",
                "type": "door",
                "door_target": 5,
                "message": "A dark cave is ahead."
            }
        ]
    },
    {
        "name": "the cave",
        "preposition": "in",
        "music": "cave.mp3",
        "bg": "cave.png",
        "inspect_list": [
            {
                "name": "cave entrance",
                "type": "door",
                "door_target": 4,
                "message": "The exit to the cave."
            }
        ]
    }
]
